huaweicloudsdkfunctiongraph/__init__.py
huaweicloudsdkfunctiongraph/v2/__init__.py
huaweicloudsdkfunctiongraph/v2/functiongraph_async_client.py
huaweicloudsdkfunctiongraph/v2/functiongraph_client.py
huaweicloudsdkfunctiongraph/v2/model/__init__.py
huaweicloudsdkfunctiongraph/v2/model/action.py
huaweicloudsdkfunctiongraph/v2/model/apig_trigger_func_info.py
huaweicloudsdkfunctiongraph/v2/model/app_template_resource_detail.py
huaweicloudsdkfunctiongraph/v2/model/async_invoke_function_request.py
huaweicloudsdkfunctiongraph/v2/model/async_invoke_function_response.py
huaweicloudsdkfunctiongraph/v2/model/batch_delete_function_triggers_request.py
huaweicloudsdkfunctiongraph/v2/model/batch_delete_function_triggers_response.py
huaweicloudsdkfunctiongraph/v2/model/batch_delete_workflows_request.py
huaweicloudsdkfunctiongraph/v2/model/batch_delete_workflows_response.py
huaweicloudsdkfunctiongraph/v2/model/callback_workflow_request_body.py
huaweicloudsdkfunctiongraph/v2/model/cancel_async_invocation_request.py
huaweicloudsdkfunctiongraph/v2/model/cancel_async_invocation_request_body.py
huaweicloudsdkfunctiongraph/v2/model/cancel_async_invocation_response.py
huaweicloudsdkfunctiongraph/v2/model/create_callback_workflow_request.py
huaweicloudsdkfunctiongraph/v2/model/create_callback_workflow_response.py
huaweicloudsdkfunctiongraph/v2/model/create_dependency_request_body.py
huaweicloudsdkfunctiongraph/v2/model/create_dependency_version_request.py
huaweicloudsdkfunctiongraph/v2/model/create_dependency_version_response.py
huaweicloudsdkfunctiongraph/v2/model/create_event_request.py
huaweicloudsdkfunctiongraph/v2/model/create_event_request_body.py
huaweicloudsdkfunctiongraph/v2/model/create_event_response.py
huaweicloudsdkfunctiongraph/v2/model/create_function_app_request.py
huaweicloudsdkfunctiongraph/v2/model/create_function_app_request_body.py
huaweicloudsdkfunctiongraph/v2/model/create_function_app_response.py
huaweicloudsdkfunctiongraph/v2/model/create_function_request.py
huaweicloudsdkfunctiongraph-3.1.184.dist-info/METADATA
huaweicloudsdkfunctiongraph-3.1.184.dist-info/WHEEL
huaweicloudsdkfunctiongraph-3.1.184.dist-info/licenses/LICENSE
huaweicloudsdkfunctiongraph-3.1.184.dist-info/RECORD
